{
	"ambient_color" : "(0.050000, 0.050000, 0.050000)",
	"camera" :
	{
		"eye" : "(-2.000000, 2.000000, 0.500000)",
		"fovy" : 30.0,
		"h" : 600,
		"look_at" : "(-1.4, 3, -0.1)",
		"up" : "(0.000000, 0.000000, 1.000000)",
		"w" : 800
	},
	"lights" :
	[
		{
			"color" : "(25.000000, 25.000000, 25.000000)",
			"dx" : "(1.500000, 0.000000, 0.000000)",
			"dy" : "(0.000000, 1.500000, 0.000000)",
			"n" : "(0.000000, 0.000000, -1.000000)",
			"o" : "(3.000000, 3.000000, 3.000000)",
			"type" : "RectLight"
		}
	],
	"objects" :
	[
		{
			"material" :
			{
				"absorb_color" : "(1, 0, 0)",
				"refl" : 0.2,
				"refr" : 0.8,
				"refr_index" : 1.5
			},
			"o" : "(-0.5, 5.14, -1.8)",
			"r" : 0.2,
			"type" : "Sphere"
		},
		{
			"material" :
			{
				"absorb_color" : "(0, 1, 0)",
				"refl" : 0.2,
				"refr" : 0.8,
				"refr_index" : 1.5
			},
			"o" : "(0, 5, -1.8)",
			"r" : 0.2,
			"type" : "Sphere"
		},
		{
			"material" :
			{
				"absorb_color" : "(0, 0, 1)",
				"refl" : 0.2,
				"refr" : 0.8,
				"refr_index" : 1.5
			},
			"o" : "(0.5, 5.14, -1.8)",
			"r" : 0.2,
			"type" : "Sphere"
		},
		{
			"material" :
			{
				"color" : "(0.5, 0.5, 1)",
				"refl" : 1
			},
			"o" : "(1.5, 6.3, -1.6)",
			"r" : 0.4,
			"type" : "Sphere"
		},
		{
			"material" :
			{
				"color" : "(1, 1, 1)",
				"diff" : 0.7,
				"refl" : 0.3,
				"texture" : "../textures/marble.bmp"
			},
			"o" : "(0, 6, -1.5)",
			"r" : 0.5,
			"texture_dx" : "(1, 0, 0)",
			"texture_dz" : "(0, 0, 1)",
			"type" : "Sphere"
		},
		{
			"d" : 2,
			"material" :
			{
				"color" : "(1, 1, 1)",
				"diff" : 0.5,
				"refl" : 0.5,
				"texture" : "../textures/floor.bmp"
			},
			"n" : "(0, 0, 1)",
			"texture_dx" : "(8, 0, 0)",
			"texture_dy" : "(0, 8, 0)",
			"type" : "Plane"
		}
	]
}
